jaraco/windows/__init__.py
jaraco/windows/batch.py
jaraco/windows/clipboard.py
jaraco/windows/cred.py
jaraco/windows/dpapi.py
jaraco/windows/environ.py
jaraco/windows/error.py
jaraco/windows/eventlog.py
jaraco/windows/inet.py
jaraco/windows/lib.py
jaraco/windows/memory.py
jaraco/windows/mmap.py
jaraco/windows/msie.py
jaraco/windows/msvc.py
jaraco/windows/net.py
jaraco/windows/power.py
jaraco/windows/privilege.py
jaraco/windows/registry.py
jaraco/windows/reparse.py
jaraco/windows/security.py
jaraco/windows/services.py
jaraco/windows/shell.py
jaraco/windows/tempfile.py
jaraco/windows/timers.py
jaraco/windows/timezone.py
jaraco/windows/ui.py
jaraco/windows/user.py
jaraco/windows/util.py
jaraco/windows/vpn.py
jaraco/windows/xmouse.py
jaraco/windows/api/__init__.py
jaraco/windows/api/clipboard.py
jaraco/windows/api/console.py
jaraco/windows/api/credential.py
jaraco/windows/api/environ.py
jaraco/windows/api/errors.py
jaraco/windows/api/event.py
jaraco/windows/api/filesystem.py
jaraco/windows/api/inet.py
jaraco/windows/api/library.py
jaraco/windows/api/memory.py
jaraco/windows/api/message.py
jaraco/windows/api/net.py
jaraco/windows/api/power.py
jaraco/windows/api/privilege.py
jaraco/windows/api/process.py
jaraco/windows/api/security.py
jaraco/windows/api/shell.py
jaraco/windows/api/system.py
jaraco/windows/api/user.py
jaraco/windows/bugs/environ-api-weirdness.py
jaraco/windows/bugs/multi_os_libc.py
jaraco/windows/compat/py310.py
jaraco/windows/filesystem/__init__.py
jaraco/windows/filesystem/backports.py
jaraco/windows/filesystem/change.py
jaraco/windows/incubator/replace-file.py
jaraco/windows/incubator/trace-symlink.py
jaraco_windows-5.10.0.dist-info/licenses/LICENSE
jaraco_windows-5.10.0.dist-info/METADATA
jaraco_windows-5.10.0.dist-info/WHEEL
jaraco_windows-5.10.0.dist-info/entry_points.txt
jaraco_windows-5.10.0.dist-info/top_level.txt
jaraco_windows-5.10.0.dist-info/RECORD
