Metadata-Version: 2.4
Name: jaraco.windows
Version: 5.10.0
Summary: Windows Routines by Jason R. Coombs
Author-email: "Jason R. Coombs" <jaraco@jaraco.com>
License-Expression: MIT
Project-URL: Source, https://github.com/jaraco/jaraco.windows
Classifier: Development Status :: 5 - Production/Stable
Classifier: Intended Audience :: Developers
Classifier: Programming Language :: Python :: 3
Classifier: Programming Language :: Python :: 3 :: Only
Classifier: Operating System :: Microsoft :: Windows
Requires-Python: >=3.9
License-File: LICENSE
Requires-Dist: more_itertools
Requires-Dist: jaraco.ui
Requires-Dist: jaraco.collections
Requires-Dist: jaraco.text
Requires-Dist: jaraco.structures>=1.1.1
Requires-Dist: path
Requires-Dist: tempora
Requires-Dist: jaraco.functools
Provides-Extra: test
Requires-Dist: pytest!=8.1.*,>=6; extra == "test"
Provides-Extra: doc
Requires-Dist: sphinx>=3.5; extra == "doc"
Requires-Dist: jaraco.packaging>=9.3; extra == "doc"
Requires-Dist: rst.linker>=1.9; extra == "doc"
Requires-Dist: furo; extra == "doc"
Requires-Dist: sphinx-lint; extra == "doc"
Requires-Dist: pywin32; extra == "doc"
Provides-Extra: check
Requires-Dist: pytest-checkdocs>=2.4; extra == "check"
Requires-Dist: pytest-ruff>=0.2.1; sys_platform != "cygwin" and extra == "check"
Provides-Extra: cover
Requires-Dist: pytest-cov; extra == "cover"
Provides-Extra: enabler
Requires-Dist: pytest-enabler>=2.2; extra == "enabler"
Provides-Extra: type
Requires-Dist: pytest-mypy; extra == "type"
Dynamic: license-file
